ssh2/__init__.py
ssh2/client.py
ssh2/config.py
ssh2/constants.py
ssh2/core.py
ssh2/errors.py
ssh2/version.py
python_ssh-0.1.1.dist-info/LICENSE
python_ssh-0.1.1.dist-info/METADATA
python_ssh-0.1.1.dist-info/WHEEL
python_ssh-0.1.1.dist-info/top_level.txt
python_ssh-0.1.1.dist-info/RECORD
